{"name":"Apple Pi: FRC Team 2067","tagline":"Programming Subteam","body":"## Learning LabVIEW\r\nThe training set that 2067 uses, which contains various programming exercises, has its own GitHub repository. Click the above button, and fork the Training repository if you're solving them as a part of the LabVIEW classes.\r\n\r\nIf you're looking for the presentations we used in the LabVIEW classes, here you go:\r\n(links)\r\n\r\nFor some other resources, here are a few links:\r\n(links)\r\n","google":"","note":"Don't delete this file! It's used internally to help with page regeneration."}